dataforge/__init__.py
dataforge/_base_session.py
dataforge/_session.py
dataforge/ingestion_session.py
dataforge/parsing_session.py
dataforge/pg.py
dataforge/post_output_session.py
dataforge/postgres_connection.py
dataforge/process_record.py
dataforge/system_configuration.py
dataforge/utils.py
dataforge/databricks/__init__.py
dataforge/databricks/_databricks_base_session.py
dataforge/databricks/_databricks_ingestion_session.py
dataforge/databricks/_databricks_parsing_session.py
dataforge/databricks/_databricks_pg.py
dataforge/snowflake/__init__.py
dataforge/snowflake/_snowflake_base_session.py
dataforge/snowflake/_snowflake_ingestion_session.py
dataforge/snowflake/_snowflake_parsing_session.py
dataforge_sdk-10.0.1.dist-info/METADATA
dataforge_sdk-10.0.1.dist-info/WHEEL
dataforge_sdk-10.0.1.dist-info/top_level.txt
dataforge_sdk-10.0.1.dist-info/RECORD
