Metadata-Version: 2.4
Name: dataforge-sdk
Version: 10.0.1
Summary: SDK for creating DataForge extensions
Author-email: Vadim Orlov <vorlov@dataforgelabs.com>
Project-URL: Homepage, https://docs.dataforgelabs.com
Project-URL: Issues, https://docs.dataforgelabs.com/hc/en-us/requests/new
Requires-Python: >=3.10
Provides-Extra: psycopg2
Requires-Dist: psycopg2-binary>=2.9; extra == "psycopg2"
